{"file_path": "../../raw_kb_v2\\category\\0TO5w000000Zao9GAC\\index.html", "content": {"article-list": [{"text": "\n\n               Adrenaline DataFlow Functions Reference Guide\n              \n", "url": "/s/article/4410213098903"}, {"text": "\n\n               Creating a SQL DataFlow\n              \n", "url": "/s/article/360042922994"}, {"text": "\n\n               Creating an Adrenaline DataFlow\n              \n", "url": "/s/article/360063698733"}, {"text": "\n\n               Easy Indexing\n              \n", "url": "/s/article/360042922954"}, {"text": "\n\n               Editing a SQL DataFlow\n              \n", "url": "/s/article/360043427793"}, {"text": "\n\n               Optimizing a SQL DataFlow\n              \n", "url": "/s/article/360042923014"}, {"text": "\n\n               Restricting Access for a SQL DataFlow\n              \n", "url": "/s/article/360042922974"}]}, "title": "\n\n             SQL DataFlows\n            \n\n", "breadcrumbs": [{"text": "\n\n              Domo\n             \n", "url": "/s/knowledge-base/"}, {"text": "\n\n              Transforming Data In Domo\n             \n", "url": "/s/topic/0TO5w000000ZamzGAC"}, {"text": "\n             SQL DataFlows\n            ", "url": null}]}