{"file_path": "../../raw_kb_v2\\article\\360043439773\\index.html", "content": {"Title": "Building Custom Connectors in Domo", "Article Body": "At Domo, our engineering team has developed hundreds of connectors but we understand the difficulties of developing for a new API platform. That's why we've created the Connector IDE, an intuitive environment for managing and creating connections between Domo and the web's most powerful APIs. If there isn't a connector built for an API you use in the AppStore, you now have the ability to build it.\n                       \n\n                        For documentation about building custom connectors in Domo, see\n                        \n                         https://developer.domo.com/connect-to-domo\n                        \n                        .", "Preview Article": "Click here to preview", "URL Name": "360043439773", "Summary\n                     \n\n\n\n\n\n\n\n\n\n\n\n\n\n\n                       Briefly describe the article. The summary is used in search results to help users find relevant articles. You can improve the accuracy of search results by including phrases that your customers use to describe this issue or topic.": "", "Article Number": "000004627", "Archived Date": "", "Language": "English", "Primary Version": "Building Custom Connectors in Domo", "Article Total View Count": "5,007", "": "", "Article Created Date": "10/24/2022, 10:17 PM", "First Published Date": "10/24/2022, 10:42 PM"}, "title": "\n              Building Custom Connectors in Domo\n             ", "breadcrumbs": [{"text": "\n\n               Domo\n              \n", "url": "/s/knowledge-base/"}, {"text": "\n\n               Using Domo APIs\n              \n", "url": "/s/topic/0TO5w000000Zan1GAC"}, {"text": "\n\n               Developer Topics\n              \n", "url": "/s/topic/0TO5w000000ZanYGAS"}]}