{"file_path": "../../raw_kb_v2\\category\\0TO5w000000ZapJGAS\\index.html", "content": {"article-list": [{"text": "adding_and_removing_accessible_content_for_a_group", "url": "/s/article/360043438873"}, {"text": "adding_users_to_domo", "url": "/s/article/360042934274"}, {"text": "changing_user_information", "url": "/s/article/360043438933"}, {"text": "controlling_access_to_cards_and_pages", "url": "/s/article/360042934254"}, {"text": "creating_and_managing_user_groups", "url": "/s/article/360042934294"}, {"text": "generating_a_list_of_users", "url": "/s/article/360042934314"}, {"text": "group_dataset_ownership_beta", "url": "/s/article/4937066992407"}, {"text": "inviting_others_to_join_domo", "url": "/s/article/360043438893"}, {"text": "removing_users_from_domo", "url": "/s/article/360042934334"}]}, "title": "user_and_group_management", "breadcrumbs": [{"text": "domo", "url": "/s/knowledge-base/"}, {"text": "administrating_domo", "url": "/s/topic/0TO5w000000ZamlGAC"}, {"text": "controlling_access_in_domo", "url": "/s/topic/0TO5w000000ZanMGAS"}, {"text": "user_and_group_management", "url": null}]}