{"file_path": "../../raw_kb_v2\\article\\360048000154\\index.html", "content": {"Title": "Changing Your Workbench Language Back to English", "Article Body": "In the event that your default Workbench language is changed from English to another language and you want to change it back to English, you have two options:\n                       \n\n\n\n                          Change the preferred language on your Workbench machine to English. This is the recommended option because it doesn't require anything but changing the preferred language back to have Workbench in your language again.\n                         \n\n\n\n                          Override the Workbench language by importing the\n                          \n                           english.reg\n                          \n                          file.\u00a0Use this option if you want to maintain the language on your machine but use Workbench in English.\n                         \n\n\n\n\n                         To override the Workbench language,\n                        \n\n\n\n\n                          Make sure Workbench is closed.\n                         \n\n\n\n                          Make sure you are an Admin on your machine.\n                         \n\n\n\n                          Navigate to\n                          \n                           Local Disk (C:) > Program Files > Domo > Workbench\n                          \n                          .\n                         \n\n\n\n                          Open\n                          \n                           English.reg\n                          \n                          .\n                         \n\n\n\n                          Choose\n                          \n                           Yes\n                          \n                          if you see a prompt like the following:\n                          \n\n\n\n\n\n\n                          Choose\n                          \n                           Yes\n                          \n                          when asked if you are sure you want to continue.\n                          \n\n\n\n\n\n\n                          Click\n                          \n                           OK\n                          \n                          when you see the following\u00a0prompt:\n                          \n\n\n\n\n\n\n                        When you next open Workbench, the UI will be in English.", "Preview Article": "Click here to preview", "URL Name": "360048000154", "Summary\n                     \n\n\n\n\n\n\n\n\n\n\n\n\n\n\n                       Briefly describe the article. The summary is used in search results to help users find relevant articles. You can improve the accuracy of search results by including phrases that your customers use to describe this issue or topic.": "", "Article Number": "000003168", "Archived Date": "", "Language": "English", "Primary Version": "Changing Your Workbench Language Back to English", "Article Total View Count": "4,662", "": "", "Article Created Date": "10/24/2022, 9:11 PM", "First Published Date": "10/24/2022, 10:39 PM"}, "title": "\n              Changing Your Workbench Language Back to English\n             ", "breadcrumbs": [{"text": "\n\n               Domo\n              \n", "url": "/s/knowledge-base/"}, {"text": "\n\n               Connecting Data To Domo\n              \n", "url": "/s/topic/0TO5w000000ZammGAC"}, {"text": "\n\n               Workbench\n              \n", "url": "/s/topic/0TO5w000000ZaoPGAS"}]}