{"file_path": "../../raw_kb_v2\\article\\360043430333\\index.html", "content": {"Title": "Creating a Project", "Article Body": "You can add a new project in the\n                        \n                         Projects & Tasks\n                        \n                        page. Once you have specified the basic information for the project, including the name, team members, privacy level (either public or private), and the optional description and due date, you can begin populating the project with tasks and giving assignments to team members.\n                       \n\n\n\n                          Video\u00a0- Creating and Managing Projects\n                         \n\n\n\n\n\n\n\n\n                         To create a new project,\n                        \n\n\n\n\n                          Open the\u00a0Projects & Tasks\u00a0page by selecting\n                          \n                           Projects and Tasks\n                          \n                          in the\n                          \n                           More\n                          \n                          menu at the top of the screen.\n                         \n\n\n\n                          Click\n                          \n\n                            Add Project\n                           \n\n                          .\n                          \n                          A\n                          \n\n                            Create New Project\n                           \n\n                          dialog opens.\n                         \n\n\n\n\n\n\n\n\n\n\n                               Tip:\n                              \n\n                             You can also open this dialog from anywhere in Domo by selecting\n                             \n                             in the app toolbar and selecting\n                             \n                              Tasks > Project\n                             \n                             .\n                            \n\n\n\n\n\n\n                          Enter the project name.\n                         \n\n\n\n                          Enter the team members for the project. As you enter letters, user names containing matching letters appear in a pop-up list. When you select a name, it is added to the field. You can add as many names to the field as you want.\n                         \n\n\n\n                          Select a privacy setting. If you select \"Public,\" anyone in your company can view, access, and edit this project. If you select \"Private,\" only the team members you selected for the project in step 4 can view and access the project.\n                         \n\n\n\n                          (Optional) Enter a project description.\n                         \n\n\n\n                          (Optional) Enter a due date for the project.\n                         \n\n\n\n                          Click\n                          \n\n                            Done\n                           \n\n                          .", "Preview Article": "Click here to preview", "URL Name": "360043430333", "Summary\n                     \n\n\n\n\n\n\n\n\n\n\n\n\n\n\n                       Briefly describe the article. The summary is used in search results to help users find relevant articles. You can improve the accuracy of search results by including phrases that your customers use to describe this issue or topic.": "", "Article Number": "000004367", "Archived Date": "", "Language": "English", "Primary Version": "Creating a Project", "Article Total View Count": "4,766", "": "", "Article Created Date": "10/24/2022, 9:45 PM", "First Published Date": "10/24/2022, 10:40 PM"}, "title": "\n              Creating a Project\n             ", "breadcrumbs": [{"text": "\n\n               Domo\n              \n", "url": "/s/knowledge-base/"}, {"text": "\n\n               Getting To Know Domo\n              \n", "url": "/s/topic/0TO5w000000ZamsGAC"}, {"text": "\n\n               Projects And Tasks\n              \n", "url": "/s/topic/0TO5w000000Zao5GAC"}]}